plugins/__init__.py
plugins/output.py
plugins/command/__init__.py
plugins/command/check_apt_security_updates.py
plugins/command/check_elasticsearch.py
plugins/command/check_elasticsearch_aws.py
plugins/command/check_puppetdb_ssh_host_keys.py
plugins/command/check_reboot_required.py
gds_nagios_plugins-1.5.0.dist-info/LICENSE
gds_nagios_plugins-1.5.0.dist-info/METADATA
gds_nagios_plugins-1.5.0.dist-info/WHEEL
gds_nagios_plugins-1.5.0.dist-info/entry_points.txt
gds_nagios_plugins-1.5.0.dist-info/top_level.txt
gds_nagios_plugins-1.5.0.dist-info/RECORD
