Metadata-Version: 2.1
Name: gds-nagios-plugins
Version: 1.5.0
Summary: nagios-plugins: a set of useful nagios plugins
Home-page: https://github.com/alphagov/nagios-plugins
Author: Tom Booth
Author-email: tombooth@gmail.com
Maintainer: Government Digital Service
License: MIT
Platform: UNKNOWN
Requires-Dist: nagioscheck (==0.1.6)
